pyapimove/__init__.py
pyapimove/cleanout.py
pyapimove-1.0.1.dist-info/METADATA
pyapimove-1.0.1.dist-info/WHEEL
pyapimove-1.0.1.dist-info/top_level.txt
pyapimove-1.0.1.dist-info/RECORD
