Metadata-Version: 2.1
Name: pyapimove
Version: 1.0.1
Summary: auto API
Author: Open
Author-email: sjsbcaksgg.s.ksv@gmail.com
Classifier: Programming Language :: Python :: 3
Classifier: Operating System :: OS Independent
Requires-Python: >=3.6
